vector_db_pkg/__init__.py
vector_db_pkg/data_ingestion.py
vector_db_pkg/preprocessing.py
vector_db_pkg/vector_db.py
vector_db_pkg/vectorization.py
vector_db_pkg-0.1.0.dist-info/LICENSE  
vector_db_pkg-0.1.0.dist-info/METADATA
vector_db_pkg-0.1.0.dist-info/WHEEL
vector_db_pkg-0.1.0.dist-info/top_level.txt
vector_db_pkg-0.1.0.dist-info/RECORD
